[{"id":"","first_name":"Merrilee","last_name":"Pedracci","ip_address":"http://dummyimage.com/209x100.png/dddddd/000000"},
{"id":"","first_name":"Christophe","last_name":"Ortiga","ip_address":"http://dummyimage.com/248x100.png/ff4444/ffffff"},
{"id":"","first_name":"Leonanie","last_name":"Simmell","ip_address":"http://dummyimage.com/106x100.png/5fa2dd/ffffff"},
{"id":"","first_name":"Odelle","last_name":"Need","ip_address":"http://dummyimage.com/232x100.png/5fa2dd/ffffff"},
{"id":"","first_name":"Mel","last_name":"Bransden","ip_address":"http://dummyimage.com/199x100.png/dddddd/000000"},
{"id":"","first_name":"Alma","last_name":"Tanguy","ip_address":"http://dummyimage.com/175x100.png/ff4444/ffffff"},
{"id":"","first_name":"Kenn","last_name":"Simonaitis","ip_address":"http://dummyimage.com/227x100.png/cc0000/ffffff"},
{"id":"","first_name":"Lawrence","last_name":"Penhall","ip_address":"http://dummyimage.com/126x100.png/dddddd/000000"},
{"id":"","first_name":"Averill","last_name":"Gummie","ip_address":"http://dummyimage.com/227x100.png/dddddd/000000"},
{"id":"","first_name":"Clovis","last_name":"Jaffray","ip_address":"http://dummyimage.com/170x100.png/ff4444/ffffff"},
{"id":"","first_name":"Jeannette","last_name":"Durant","ip_address":"http://dummyimage.com/241x100.png/ff4444/ffffff"},
{"id":"","first_name":"Kerry","last_name":"Masden","ip_address":"http://dummyimage.com/179x100.png/dddddd/000000"},
{"id":"","first_name":"Alma","last_name":"Rowter","ip_address":"http://dummyimage.com/137x100.png/cc0000/ffffff"},
{"id":"","first_name":"Creight","last_name":"Macauley","ip_address":"http://dummyimage.com/201x100.png/cc0000/ffffff"},
{"id":"","first_name":"Marcille","last_name":"Diver","ip_address":"http://dummyimage.com/216x100.png/5fa2dd/ffffff"},
{"id":"","first_name":"Pepita","last_name":"Cicerone","ip_address":"http://dummyimage.com/192x100.png/dddddd/000000"},
{"id":"","first_name":"Francis","last_name":"Cattanach","ip_address":"http://dummyimage.com/109x100.png/cc0000/ffffff"},
{"id":"","first_name":"Tad","last_name":"Pedrol","ip_address":"http://dummyimage.com/223x100.png/ff4444/ffffff"},
{"id":"","first_name":"Jason","last_name":"Ullyott","ip_address":"http://dummyimage.com/182x100.png/5fa2dd/ffffff"},
{"id":"","first_name":"Raffaello","last_name":"Brader","ip_address":"http://dummyimage.com/149x100.png/ff4444/ffffff"},
{"id":"","first_name":"Benton","last_name":"Dingsdale","ip_address":"http://dummyimage.com/129x100.png/dddddd/000000"},
{"id":"","first_name":"Melissa","last_name":"Fury","ip_address":"http://dummyimage.com/182x100.png/5fa2dd/ffffff"},
{"id":"","first_name":"Zollie","last_name":"Oxbrough","ip_address":"http://dummyimage.com/166x100.png/cc0000/ffffff"},
{"id":"","first_name":"Amanda","last_name":"Stollwerk","ip_address":"http://dummyimage.com/208x100.png/ff4444/ffffff"},
{"id":"","first_name":"Jessalyn","last_name":"Pervew","ip_address":"http://dummyimage.com/110x100.png/5fa2dd/ffffff"},
{"id":"","first_name":"Reeta","last_name":"Roseman","ip_address":"http://dummyimage.com/176x100.png/dddddd/000000"},
{"id":"","first_name":"Adam","last_name":"Kaley","ip_address":"http://dummyimage.com/110x100.png/5fa2dd/ffffff"},
{"id":"","first_name":"Georg","last_name":"Carrett","ip_address":"http://dummyimage.com/137x100.png/ff4444/ffffff"},
{"id":"","first_name":"Benedicta","last_name":"Sambals","ip_address":"http://dummyimage.com/223x100.png/cc0000/ffffff"},
{"id":"","first_name":"Stillman","last_name":"Dantesia","ip_address":"http://dummyimage.com/171x100.png/ff4444/ffffff"},
{"id":"","first_name":"Zacharias","last_name":"Masters","ip_address":"http://dummyimage.com/121x100.png/cc0000/ffffff"},
{"id":"","first_name":"Alan","last_name":"de la Tremoille","ip_address":"http://dummyimage.com/157x100.png/cc0000/ffffff"},
{"id":"","first_name":"Wallie","last_name":"Clouston","ip_address":"http://dummyimage.com/125x100.png/dddddd/000000"},
{"id":"","first_name":"Gus","last_name":"Bilt","ip_address":"http://dummyimage.com/149x100.png/ff4444/ffffff"},
{"id":"","first_name":"Torrey","last_name":"Bartalini","ip_address":"http://dummyimage.com/129x100.png/dddddd/000000"},
{"id":"","first_name":"Theadora","last_name":"Ellings","ip_address":"http://dummyimage.com/109x100.png/dddddd/000000"},
{"id":"","first_name":"Prent","last_name":"McGauhy","ip_address":"http://dummyimage.com/156x100.png/dddddd/000000"},
{"id":"","first_name":"Brit","last_name":"Rude","ip_address":"http://dummyimage.com/244x100.png/5fa2dd/ffffff"},
{"id":"","first_name":"Karia","last_name":"Franzoli","ip_address":"http://dummyimage.com/127x100.png/5fa2dd/ffffff"},
{"id":"","first_name":"Martina","last_name":"Tweedlie","ip_address":"http://dummyimage.com/197x100.png/5fa2dd/ffffff"},
{"id":"","first_name":"Lyndsay","last_name":"Roft","ip_address":"http://dummyimage.com/194x100.png/dddddd/000000"},
{"id":"","first_name":"Devlen","last_name":"Grinnov","ip_address":"http://dummyimage.com/136x100.png/ff4444/ffffff"},
{"id":"","first_name":"Nedda","last_name":"Shimony","ip_address":"http://dummyimage.com/182x100.png/cc0000/ffffff"},
{"id":"","first_name":"Wright","last_name":"Corneljes","ip_address":"http://dummyimage.com/163x100.png/cc0000/ffffff"},
{"id":"","first_name":"Liesa","last_name":"Jonathon","ip_address":"http://dummyimage.com/237x100.png/5fa2dd/ffffff"},
{"id":"","first_name":"Jared","last_name":"Ponder","ip_address":"http://dummyimage.com/155x100.png/5fa2dd/ffffff"},
{"id":"","first_name":"Beryl","last_name":"Verlinde","ip_address":"http://dummyimage.com/137x100.png/5fa2dd/ffffff"},
{"id":"","first_name":"Alyda","last_name":"Sturdey","ip_address":"http://dummyimage.com/195x100.png/cc0000/ffffff"},
{"id":"","first_name":"Arlie","last_name":"Dimitrie","ip_address":"http://dummyimage.com/236x100.png/cc0000/ffffff"},
{"id":"","first_name":"Cesare","last_name":"Lauderdale","ip_address":"http://dummyimage.com/162x100.png/cc0000/ffffff"},
{"id":"","first_name":"Micki","last_name":"Alison","ip_address":"http://dummyimage.com/128x100.png/5fa2dd/ffffff"},
{"id":"","first_name":"Keefe","last_name":"Petegre","ip_address":"http://dummyimage.com/192x100.png/cc0000/ffffff"},
{"id":"","first_name":"Gabbie","last_name":"Jakubowicz","ip_address":"http://dummyimage.com/212x100.png/5fa2dd/ffffff"},
{"id":"","first_name":"Melesa","last_name":"Oakenford","ip_address":"http://dummyimage.com/227x100.png/ff4444/ffffff"},
{"id":"","first_name":"Dido","last_name":"Raatz","ip_address":"http://dummyimage.com/244x100.png/cc0000/ffffff"},
{"id":"","first_name":"Danila","last_name":"Stroder","ip_address":"http://dummyimage.com/106x100.png/cc0000/ffffff"},
{"id":"","first_name":"Gratia","last_name":"Basnall","ip_address":"http://dummyimage.com/139x100.png/dddddd/000000"},
{"id":"","first_name":"Rebeca","last_name":"Spriddle","ip_address":"http://dummyimage.com/129x100.png/dddddd/000000"},
{"id":"","first_name":"Arty","last_name":"Favelle","ip_address":"http://dummyimage.com/166x100.png/dddddd/000000"},
{"id":"","first_name":"Yank","last_name":"Addis","ip_address":"http://dummyimage.com/141x100.png/5fa2dd/ffffff"},
{"id":"","first_name":"Binky","last_name":"Bough","ip_address":"http://dummyimage.com/118x100.png/5fa2dd/ffffff"},
{"id":"","first_name":"Brear","last_name":"Hawkwood","ip_address":"http://dummyimage.com/224x100.png/5fa2dd/ffffff"},
{"id":"","first_name":"Bea","last_name":"Bevans","ip_address":"http://dummyimage.com/223x100.png/dddddd/000000"},
{"id":"","first_name":"Tally","last_name":"Dallman","ip_address":"http://dummyimage.com/239x100.png/5fa2dd/ffffff"},
{"id":"","first_name":"Tiena","last_name":"Jowers","ip_address":"http://dummyimage.com/132x100.png/cc0000/ffffff"},
{"id":"","first_name":"Troy","last_name":"Panas","ip_address":"http://dummyimage.com/177x100.png/ff4444/ffffff"},
{"id":"","first_name":"Gene","last_name":"Sconce","ip_address":"http://dummyimage.com/229x100.png/cc0000/ffffff"},
{"id":"","first_name":"Albertina","last_name":"Cleeton","ip_address":"http://dummyimage.com/144x100.png/5fa2dd/ffffff"},
{"id":"","first_name":"Libbi","last_name":"Vagg","ip_address":"http://dummyimage.com/226x100.png/dddddd/000000"},
{"id":"","first_name":"Geno","last_name":"Easby","ip_address":"http://dummyimage.com/197x100.png/dddddd/000000"},
{"id":"","first_name":"Paulina","last_name":"Samms","ip_address":"http://dummyimage.com/184x100.png/cc0000/ffffff"},
{"id":"","first_name":"Hort","last_name":"Oppie","ip_address":"http://dummyimage.com/215x100.png/ff4444/ffffff"},
{"id":"","first_name":"Justen","last_name":"Ambroz","ip_address":"http://dummyimage.com/204x100.png/dddddd/000000"},
{"id":"","first_name":"Magda","last_name":"Madgwick","ip_address":"http://dummyimage.com/187x100.png/dddddd/000000"},
{"id":"","first_name":"Shir","last_name":"Pessel","ip_address":"http://dummyimage.com/167x100.png/cc0000/ffffff"},
{"id":"","first_name":"Carlie","last_name":"Keilloh","ip_address":"http://dummyimage.com/141x100.png/5fa2dd/ffffff"},
{"id":"","first_name":"Pepe","last_name":"Kearley","ip_address":"http://dummyimage.com/220x100.png/cc0000/ffffff"},
{"id":"","first_name":"Corinna","last_name":"Pallin","ip_address":"http://dummyimage.com/216x100.png/cc0000/ffffff"},
{"id":"","first_name":"Pepi","last_name":"Clissett","ip_address":"http://dummyimage.com/198x100.png/dddddd/000000"},
{"id":"","first_name":"Ban","last_name":"MacVay","ip_address":"http://dummyimage.com/161x100.png/cc0000/ffffff"},
{"id":"","first_name":"Natalee","last_name":"Corsar","ip_address":"http://dummyimage.com/123x100.png/cc0000/ffffff"},
{"id":"","first_name":"Grove","last_name":"Faulkes","ip_address":"http://dummyimage.com/234x100.png/dddddd/000000"},
{"id":"","first_name":"Ester","last_name":"Duesbury","ip_address":"http://dummyimage.com/231x100.png/5fa2dd/ffffff"},
{"id":"","first_name":"Robert","last_name":"Tonepohl","ip_address":"http://dummyimage.com/108x100.png/dddddd/000000"},
{"id":"","first_name":"Page","last_name":"Eccles","ip_address":"http://dummyimage.com/237x100.png/5fa2dd/ffffff"},
{"id":"","first_name":"Gwenette","last_name":"Newrick","ip_address":"http://dummyimage.com/142x100.png/cc0000/ffffff"},
{"id":"","first_name":"Reba","last_name":"Furnell","ip_address":"http://dummyimage.com/138x100.png/cc0000/ffffff"},
{"id":"","first_name":"Mitchel","last_name":"Bickardike","ip_address":"http://dummyimage.com/238x100.png/cc0000/ffffff"},
{"id":"","first_name":"Roxanne","last_name":"Sonner","ip_address":"http://dummyimage.com/223x100.png/dddddd/000000"},
{"id":"","first_name":"Elmore","last_name":"Lahrs","ip_address":"http://dummyimage.com/240x100.png/dddddd/000000"},
{"id":"","first_name":"Hershel","last_name":"Conroy","ip_address":"http://dummyimage.com/177x100.png/5fa2dd/ffffff"},
{"id":"","first_name":"Dannie","last_name":"Madgett","ip_address":"http://dummyimage.com/189x100.png/dddddd/000000"},
{"id":"","first_name":"Cyrillus","last_name":"Gregg","ip_address":"http://dummyimage.com/143x100.png/cc0000/ffffff"},
{"id":"","first_name":"Jenn","last_name":"Burle","ip_address":"http://dummyimage.com/102x100.png/5fa2dd/ffffff"},
{"id":"","first_name":"Heddi","last_name":"Schaumann","ip_address":"http://dummyimage.com/134x100.png/5fa2dd/ffffff"},
{"id":"","first_name":"Britney","last_name":"Harpham","ip_address":"http://dummyimage.com/100x100.png/dddddd/000000"},
{"id":"","first_name":"Sherry","last_name":"Gepheart","ip_address":"http://dummyimage.com/123x100.png/ff4444/ffffff"},
{"id":"","first_name":"Sonnie","last_name":"McGorley","ip_address":"http://dummyimage.com/113x100.png/5fa2dd/ffffff"},
{"id":"","first_name":"Nada","last_name":"Penni","ip_address":"http://dummyimage.com/164x100.png/ff4444/ffffff"},
{"id":"","first_name":"Reeba","last_name":"O'Curran","ip_address":"http://dummyimage.com/243x100.png/dddddd/000000"}]